edwh_restic_plugin/__about__.py
edwh_restic_plugin/__init__.py
edwh_restic_plugin/env.py
edwh_restic_plugin/forget.py
edwh_restic_plugin/helpers.py
edwh_restic_plugin/restictypes.py
edwh_restic_plugin/tasks.py
edwh_restic_plugin/repositories/__init__.py
edwh_restic_plugin/repositories/b2.py
edwh_restic_plugin/repositories/hetzner.py
edwh_restic_plugin/repositories/local.py
edwh_restic_plugin/repositories/oracle.py
edwh_restic_plugin/repositories/r2.py
edwh_restic_plugin/repositories/s3.py
edwh_restic_plugin/repositories/sftp.py
edwh_restic_plugin/repositories/swift.py
edwh_restic_plugin-0.13.1.dist-info/METADATA
edwh_restic_plugin-0.13.1.dist-info/WHEEL
edwh_restic_plugin-0.13.1.dist-info/entry_points.txt
edwh_restic_plugin-0.13.1.dist-info/RECORD
