Metadata-Version: 2.3
Name: edwh-restic-plugin
Version: 0.13.1
Project-URL: Documentation, https://github.com/educationwarehouse/edwh-restic-plugin#readme
Project-URL: Issues, https://github.com/educationwarehouse/edwh-restic-plugin/issues
Project-URL: Source, https://github.com/educationwarehouse/edwh-restic-plugin
Author-email: Remco Boerma <remco.b@educationwarehouse.nl>, Robin van der Noord <robin.vdn@educationwarehouse.nl>
Classifier: Development Status :: 4 - Beta
Classifier: Programming Language :: Python
Classifier: Programming Language :: Python :: 3.10
Classifier: Programming Language :: Python :: 3.11
Classifier: Programming Language :: Python :: 3.12
Classifier: Programming Language :: Python :: Implementation :: CPython
Classifier: Programming Language :: Python :: Implementation :: PyPy
Requires-Python: >=3.10
Requires-Dist: edwh
Requires-Dist: termcolor
Requires-Dist: tqdm
Requires-Dist: typing-extensions
Provides-Extra: dev
Requires-Dist: black; extra == 'dev'
Requires-Dist: hatch; extra == 'dev'
